{
  "unversionedId": "staking/staking-overview",
  "id": "staking/staking-overview",
  "title": "Overview",
  "description": "Zilliqa Seed Node Staking Overview",
  "source": "@site/docs/staking/overview.md",
  "sourceDirName": "staking",
  "slug": "/staking/staking-overview",
  "permalink": "/docs/staking/staking-overview",
  "draft": false,
  "editUrl": "https://github.com/Zilliqa/dev-portal/tree/master/docs/staking/overview.md",
  "tags": [],
  "version": "current",
  "frontMatter": {
    "id": "staking-overview",
    "title": "Overview",
    "keywords": [
      "staking",
      "overview",
      "ssn",
      "seed node",
      "zilliqa"
    ],
    "description": "Zilliqa Seed Node Staking Overview"
  },
  "sidebar": "StakingSidebar",
  "next": {
    "title": "Disclaimer",
    "permalink": "/docs/staking/staking-disclaimer"
  }
}